ifmO3rViewer/__init__.py
ifmO3rViewer/colorbar.py
ifmO3rViewer/gui.py
ifmO3rViewer/startViewer.py
ifmO3rViewer/viewer.py
ifmO3rViewer-0.1.0.dist-info/LICENSE
ifmO3rViewer-0.1.0.dist-info/METADATA
ifmO3rViewer-0.1.0.dist-info/WHEEL
ifmO3rViewer-0.1.0.dist-info/top_level.txt
ifmO3rViewer-0.1.0.dist-info/RECORD
