Metadata-Version: 2.1
Name: ifmO3rViewer
Version: 0.1.0
Summary: 3D viewer for ifmO3R
Home-page: https://www.ifm3d.com
Author: Sebastian Voegele
Author-email: sebastian.voegele@ifm.com
License: Apache 2.0 License
Keywords: ifm,o3r,3d,viewer
Platform: UNKNOWN
Classifier: License :: OSI Approved :: Apache Software License
Classifier: Programming Language :: Python :: 3
Requires-Dist: ifmO3r (>=0.0.10)
Requires-Dist: pyqtgraph (==0.11.1)
Requires-Dist: pyopengl (==3.1.5)
Requires-Dist: PyQt5 (==5.15.2)
